sloth_ci/ext/docker_exec.py
sloth_ci.ext.docker_exec-1.1.3.dist-info/DESCRIPTION.rst
sloth_ci.ext.docker_exec-1.1.3.dist-info/METADATA
sloth_ci.ext.docker_exec-1.1.3.dist-info/RECORD
sloth_ci.ext.docker_exec-1.1.3.dist-info/WHEEL
sloth_ci.ext.docker_exec-1.1.3.dist-info/metadata.json
sloth_ci.ext.docker_exec-1.1.3.dist-info/top_level.txt
