Metadata-Version: 2.0
Name: sloth-ci.ext.docker-exec
Version: 1.1.3
Summary: Docker executor for Sloth CI
Home-page: https://bitbucket.org/moigagoo/sloth-ci-extensions
Author: Konstantin Molchanov
Author-email: moigagoo@live.com
License: MIT
Platform: UNKNOWN
Classifier: Development Status :: 5 - Production/Stable
Classifier: Intended Audience :: Developers
Classifier: Natural Language :: English
Classifier: Programming Language :: Python
Classifier: Programming Language :: Python :: 3
Requires-Dist: awesome-slugify
Requires-Dist: docker-py
Requires-Dist: sloth-ci (>=2.0.1)
